reallife_client_mac/__init__.py
reallife_client_mac/core.py
reallife_client_mac/log.py
reallife_client_mac/server.py
reallife_client_mac-0.1.25.dist-info/METADATA
reallife_client_mac-0.1.25.dist-info/WHEEL
reallife_client_mac-0.1.25.dist-info/top_level.txt
reallife_client_mac-0.1.25.dist-info/RECORD
