Metadata-Version: 2.4
Name: reallife-client-mac
Version: 0.1.25
Summary: Add your description here
Requires-Python: >=3.10
Requires-Dist: appscriptz==1.0.4
Requires-Dist: apscheduler>=3.11.0
Requires-Dist: canvaz==1.0.1
Requires-Dist: kanbanz==0.2.8
Requires-Dist: requests>=2.32.3
Requires-Dist: toml==0.10.2
Requires-Dist: uvicorn==0.35.0
